{
  "version": "1.3.12.20181021",
  "createdAt": "2017-03-02",
  "rules": [
    {
      "description": "Downgrade B5200",
      "origin": "^https://(www|m).b5200.net/",
      "exclude": "",
      "methods": [],
      "types": [],
      "target": "http://$1.b5200.net/",
      "example": "",
      "enable": true,
      "process": "",
      "_originRe": {}
    },
    {
      "description": "HTTPS 云来阁",
      "origin": "^https?://www.yunlaige.com/",
      "exclude": "",
      "methods": [],
      "types": [],
      "target": "https://m.yunlaige.com/",
      "example": "",
      "enable": true,
      "process": "",
      "_originRe": {}
    },
    {
      "description": "Google 翻译",
      "origin": "^https?://translate.google.com/",
      "exclude": "",
      "methods": [],
      "types": [],
      "target": "https://translate.google.cn/",
      "example": "",
      "enable": true,
      "process": "",
      "_originRe": {}
    },
    {
      "description": "Google -> 科大 1",
      "origin": "^https?://(ajax|fonts).googleapis.com",
      "exclude": "",
      "methods": [],
      "types": [],
      "target": "https://$1.proxy.ustclug.org",
      "example": "https://fonts.googleapis.com/css?family=Tangerine",
      "enable": true,
      "process": "",
      "_originRe": {}
    },
    {
      "description": "Google -> 科大 2",
      "origin": "^https?://themes.googleusercontent.com",
      "exclude": "",
      "methods": [],
      "types": [],
      "target": "https://google-themes.proxy.ustclug.org",
      "example": "https://themes.googleusercontent.com/static/fonts/antic/v4/hEa8XCNM7tXGzD0Uk0AipA.ttf",
      "enable": true,
      "process": "",
      "_originRe": {}
    },
    {
      "description": "直接登录：豆瓣跳过注册页面",
      "origin": "^https?://www.douban.com/accounts/register$",
      "exclude": "",
      "methods": [],
      "types": [
        "main_frame"
      ],
      "target": "https://www.douban.com/accounts/login",
      "example": "http://www.douban.com/accounts/register",
      "enable": true,
      "process": "",
      "_originRe": {}
    },
    {
      "description": "直接登录：用户样式库直接选择用户名密码登录模式",
      "origin": "^https://userstyles.org/login$",
      "exclude": "",
      "methods": [],
      "types": [
        "main_frame"
      ],
      "target": "https://userstyles.org/login?view=password",
      "example": "https://userstyles.org/login",
      "enable": true,
      "process": "",
      "_originRe": {}
    },
    {
      "description": "直接登录：知乎",
      "origin": "^https?://www.zhihu.com/#?signup.*",
      "exclude": "",
      "methods": [],
      "types": [
        "main_frame"
      ],
      "target": "https://www.zhihu.com/signin",
      "example": "https://www.zhihu.com/signup?next=%2F",
      "enable": true,
      "process": "",
      "_originRe": {}
    },
    {
      "description": "直接下载：Dropbpx 跳过下载页直接进入直链",
      "origin": "^https://www.dropbox.com/s/(.*)\\?dl=0",
      "exclude": "",
      "methods": [],
      "types": [
        "main_frame"
      ],
      "target": "https://dl.dropboxusercontent.com/s/$1",
      "example": "https://www.dropbox.com/s/rnx6mxpe5s44pa2/Redirector.txt?dl=0",
      "enable": true,
      "process": "",
      "_originRe": {}
    },
    {
      "description": "去除跳转：Busy外链——注意安全",
      "origin": "^https://busy.org/exit\\?url=(\\S+)",
      "exclude": "",
      "methods": [],
      "types": [
        "main_frame"
      ],
      "target": "$1",
      "example": "https://busy.org/exit?url=https%3A%2F%2Fmp.weixin.qq.com%2Fs%2FYNsOmb38UEP_vhjUARDn-w",
      "enable": true,
      "process": "urlDecode",
      "_originRe": {}
    },
    {
      "description": "去除跳转：垃圾站",
      "origin": "^https?://www.spmke.com/source/bd.php\\?(https?://.+)",
      "exclude": "",
      "methods": [],
      "types": [
        "main_frame"
      ],
      "target": "$1",
      "example": "http://www.spmke.com/source/bd.php?http://www.baidu.com",
      "enable": true,
      "process": "",
      "_originRe": {}
    },
    {
      "description": "去除跳转：知乎外链——注意安全",
      "origin": "^https?://link.zhihu.com/\\?target=(\\S+)",
      "exclude": "",
      "methods": [],
      "types": [],
      "target": "$1",
      "example": "https://link.zhihu.com/?target=https%3A//www.jd.com",
      "enable": true,
      "process": "urlDecode",
      "_originRe": {}
    },
    {
      "description": "去除嵌套：QQ浏览器分享",
      "origin": "^https?://news.html5.qq.com/share/\\d+\\?url=http(.+)",
      "exclude": "",
      "methods": [],
      "types": [
        "main_frame"
      ],
      "target": "http$1",
      "example": "https://news.html5.qq.com/share/111111?url=http%3A%2F%2Fkuaibao.qq.com%2Fs%2F20180803A1NB7L00&*",
      "enable": true,
      "process": "urlDecode",
      "_originRe": {}
    },
    {
      "description": "去除尾巴：天天快报",
      "origin": "^https?://kuaibao.qq.com/s/(\\w+)&.*",
      "exclude": "",
      "methods": [],
      "types": [
        "main_frame"
      ],
      "target": "https://kuaibao.qq.com/s/$1",
      "example": "https://kuaibao.qq.com/s/20180803A1NB7L00&*",
      "enable": true,
      "process": "",
      "_originRe": {}
    },
    {
      "description": "去除尾巴：今日头条",
      "origin": "^https?://(www|m).toutiao(cdn)?.com/(a|i)(\\d+)/\\?.*",
      "exclude": "",
      "methods": [],
      "types": [
        "main_frame"
      ],
      "target": "https://$1.toutiao.com/$3$4",
      "example": "https://www.toutiao.com/i6385720374801203714/?tt_from=mobile_qq&utm_campaign=client_share&app=news_article&utm_source=mobile_qq&utm_medium=toutiao_ios",
      "enable": true,
      "process": "",
      "_originRe": {}
    },
    {
      "description": "去除尾巴：Twitter 短链判断失败时混入的尾部中文等字符",
      "origin": "^https?://t.co/(\\w{10}).+",
      "exclude": "",
      "methods": [],
      "types": [
        "main_frame"
      ],
      "target": "https://t.co/$1",
      "example": "http://t.co/shSgWRTz51张佳玮写字的地方",
      "enable": true,
      "process": "",
      "_originRe": {}
    },
    {
      "description": "去除尾巴：优酷",
      "origin": "^https?://v(-wb)?.youku.com/v_show/id_(\\w+)(==_?.*)?.html(\\?.*)?",
      "exclude": "https?://v.youku.com/v_show/id_\\w+.html$",
      "methods": [],
      "types": [
        "main_frame"
      ],
      "target": "https://v.youku.com/v_show/id_$2.html",
      "example": "https://v-wb.youku.com/v_show/id_XMzk0NTczMDY0NA==.html?from=y1.2-1-105.3.5-2.1-1-1-4-0",
      "enable": true,
      "process": "",
      "_originRe": {}
    },
    {
        "description": "阅读模式：网易新闻APP分享产生地址重定向至更适合网页阅读版本",
        "origin": "^https?://c.m.163.com/news/a/(\\w+).html(\\?.*)?",
        "exclude": "",
        "methods": [],
        "types": [
          "main_frame"
        ],
        "target": "https://3g.163.com/news/article/$1.html",
        "example": "",
        "enable": true,
        "process": "",
        "_originRe": {}
    },
    {
      "description": "阅读模式：Mozest 广场无图版转至完整版",
      "origin": "^https?://g.mozest.com/archiver/tid-(\\d+).html$",
      "exclude": "",
      "methods": [],
      "types": [
        "main_frame"
      ],
      "target": "http://g.mozest.com/viewthread.php?tid=$1",
      "example": "http://g.mozest.com/archiver/tid-38916.html",
      "enable": true,
      "process": "",
      "_originRe": {}
    },
    {
        "description": "阅读模式：新浪博客文章自动跳转到移动版",
        "origin": "^https?://blog.sina.com.cn/(s/blog_\\w+.html).*",
        "exclude": "",
        "methods": [],
        "types": [
          "main_frame"
        ],
        "target": "https://blog.sina.cn/dpool/blog/$1",
        "example": "http://blog.sina.com.cn/s/blog_450a32940102xow3.html",
        "enable": true,
        "process": "",
        "_originRe": {}
    },
    {
      "description": "阅读模式：跳过微博看看框架",
      "origin": "^https?://weibo.wbdacdn.com/url/t/(\\w{7})/?",
      "exclude": "",
      "methods": [],
      "types": [
        "main_frame"
      ],
      "target": "https://t.cn/$1",
      "example": "http://weibo.wbdacdn.com/url/t/R5mLykn",
      "enable": true,
      "process": "",
      "_originRe": {}
    },
    {
      "description": "阅读模式：将特定微博信息从微博看看跳转至微博HTML5版",
      "origin": "^https?://weibo.wbdacdn.com/user/\\d+/status(\\d+).html.*",
      "exclude": "",
      "methods": [],
      "types": [
        "main_frame"
      ],
      "target": "https://m.weibo.cn/status/$1",
      "example": "http://weibo.wbdacdn.com/user/2803301701/status4074010167896825.html#utm_source=rss",
      "enable": true,
      "process": "",
      "_originRe": {}
    },
    {
      "description": "阅读模式：微博文章自动跳转到移动版",
      "origin": "^https?://(www.)?weibo.com/ttarticle/p/show",
      "exclude": "",
      "methods": [],
      "types": [
        "main_frame"
      ],
      "target": "https://media.weibo.cn/article",
      "example": "http://weibo.com/ttarticle/p/show?id=2309404056722711967901",
      "enable": true,
      "process": "",
      "_originRe": {}
    },
    {
      "description": "自动全文：FT中文网",
      "origin": "^https?://www.ftchinese.com/story/(\\d+)$",
      "exclude": "",
      "methods": [],
      "types": [
        "main_frame"
      ],
      "target": "https://www.ftchinese.com/story/$1?full=y",
      "example": "http://www.ftchinese.com/story/001053184",
      "enable": true,
      "process": "",
      "_originRe": {}
    },
    {
      "description": "自动全文：观察者网",
      "origin": "^https?://www.guancha.cn/(\\S+/\\d{4}_\\d{2}_\\d{2}_\\d+)(_[1-9])?.shtml.*",
      "exclude": "",
      "methods": [],
      "types": [
        "main_frame"
      ],
      "target": "https://www.guancha.cn/$1_s.shtml",
      "example": "https://www.guancha.cn/society/2018_07_18_464635.shtml?s=z",
      "enable": true,
      "process": "",
      "_originRe": {}
    },
    {
      "description": "自动全文：法律图书馆",
      "origin": "^https?://www.law-lib.com/law/law_view.asp\\?id=(\\d+)$",
      "exclude": "",
      "methods": [],
      "types": [
        "main_frame"
      ],
      "target": "http://www.law-lib.com/law/law_view1.asp?id=$1",
      "example": "http://www.law-lib.com/law/law_view.asp?id=499805",
      "enable": true,
      "process": "",
      "_originRe": {}
    },
    {
      "description": "原图显示：Lofter；可作用于InoReader",
      "origin": "^https?://(imglf(\\d)?.nosdn.127.net/img/\\w+.(jpg|jpeg|gif|png|bmp|webp))\\?.*",
      "exclude": "",
      "methods": [],
      "types": [
        "main_frame",
        "image"
      ],
      "target": "https://$1",
      "example": "https://imglf.nosdn.127.net/img/T0VLUWtpQlNHSmVHYlM0QU01cElqRE0vM09ETzRKTEtjK3hROFpqSk9QMm1GWXlaL2EwQ1hBPT0.jpeg?imageView&thumbnail=500x10000&quality=96&stripmeta=0&type=jpg%7Cwatermark&type=1&dx=0&gravity=southwest&dissolve=100&image=aW1nL3N5cy9zZWxlY3Rpb24tcnNzLXdhdGVybWFyay5wbmc=&ssitoken_1479551598431_",
      "enable": true,
      "process": "",
      "_originRe": {}
    },
    {
      "description": "原图显示：3DM游戏网",
      "origin": "^https?://(img.3dmgame.com/uploads/allimg/\\d+/\\d+_\\d+_\\d+)_lit.(jpg|png)",
      "exclude": "",
      "methods": [],
      "types": [],
      "target": "https://$1.$2",
      "example": "https://img.3dmgame.com/uploads/allimg/171123/390_171123162159_20_lit.jpg",
      "enable": true,
      "process": "",
      "_originRe": {}
    },
    {
      "description": "原图显示：卡饭图床",
      "origin": "^https?://a.ikafan.com/attachment/forum/(.+)",
      "exclude": "",
      "methods": [],
      "types": [
        "main_frame",
        "image"
      ],
      "target": "https://fj.ikafan.com/attachment/forum/$1",
      "example": "http://a.ikafan.com/attachment/forum/201312/21/132325xdicdd42rlfg39fb.png",
      "enable": true,
      "process": "",
      "_originRe": {}
    },
    {
      "description": "原图显示：新浪缩略图1解码",
      "origin": "^https?://s.img.mix.sina.com.cn/\\S+img=(https?)?(:|%3A)?(//|%2F%2F)?(\\S+)(&size=.*)?",
      "exclude": "",
      "methods": [],
      "types": [
        "main_frame",
        "image"
      ],
      "target": "https://$4",
      "example": "https://s.img.mix.sina.com.cn/api/auto/resize?size=320_0&img=//n.sinaimg.cn/news/transform/299/w180h119/20180716/d6WY-hfkffak6676180.jpg",
      "enable": true,
      "process": "urlDecode",
      "_originRe": {}
    },
    {
      "description": "原图显示：新浪缩略图2去后缀",
      "origin": "^https?://(\\w).sinaimg.cn/(\\S+)&size=.*",
      "exclude": "",
      "methods": [],
      "types": [
        "main_frame",
        "image"
      ],
      "target": "https://$1.sinaimg.cn/$2",
      "example": "http://n.sinaimg.cn/sinacn12/156/w640h316/20180717/750b-hfkffam1788263.jpg&size=130_870718/besy-hfnsvza0055818.jpg&size=130_87",
      "enable": true,
      "process": "",
      "_originRe": {}
    },
    {
      "description": "原图显示：Tumblr；可作用于InoReader",
      "origin": "^https?://(\\d+).media.tumblr.com/(.+tumblr_\\w+_)500.(jpg|jpeg|gif|png|bmp|webp)(\\?ssitoken_\\d+_)?$",
      "exclude": "",
      "methods": [],
      "types": [
        "main_frame",
        "image"
      ],
      "target": "https://$1.media.tumblr.com/$21280.$3",
      "example": "https://68.media.tumblr.com/3beca4f8c1e028a29e87394de17c86b1/tumblr_o2qh8ztGAt1r7hrego2_500.jpg",
      "enable": true,
      "process": "",
      "_originRe": {}
    },
    {
      "description": "原图显示：Tumblr 失效的外链图床；测试见：https://www.reddit.com/domain/$1.media.tumblr.com/",
      "origin": "^https?://(41|65|67|78).media.tumblr.com/",
      "exclude": "",
      "methods": [],
      "types": [
        "main_frame",
        "image"
      ],
      "target": "https://68.media.tumblr.com/",
      "example": "http://41.media.tumblr.com/2e2b4f5c659dca9b09d9b8a881656d82/tumblr_o0y4zmaRxk1t52mpao1_500.jpg",
      "enable": true,
      "process": "",
      "_originRe": {}
    },
    {
      "description": "原图显示：修复挖矿网 RSS 输出错误",
      "origin": "^https://wk588.com/wp-content/uploads/(\\d{4}/\\d{2}/\\S+.(jpg|jpeg|gif|png|bmp|webp))$",
      "exclude": "",
      "methods": [],
      "types": [
        "main_frame",
        "image"
      ],
      "target": "https://img.wk588.com/wp-content/uploads/$1",
      "example": "https://wk588.com/wp-content/uploads/2018/01/134011hyjgwm9qmukzumy2.png",
      "enable": true,
      "process": "",
      "_originRe": {}
    }
  ]
}
